[{"id":"f8469ebc-02d7-49b8-9e90-ed4001f75cbb","fstName":"Tony","lstName":"Stark","comName":"StarkInd","emails":["tony@starkind.com","stark@starkind.com","tony.tony@starkind.com","stark.stark@starkind.com","tony.stark@starkind.com","stark.tony@starkind.com","t.stark@starkind.com","s.tony@starkind.com","tony@starkind.me","stark@starkind.me","tony.tony@starkind.me","stark.stark@starkind.me","tony.stark@starkind.me","stark.tony@starkind.me","t.stark@starkind.me","s.tony@starkind.me","tony@starkind.ua","stark@starkind.ua","tony.tony@starkind.ua","stark.stark@starkind.ua","tony.stark@starkind.ua","stark.tony@starkind.ua","t.stark@starkind.ua","s.tony@starkind.ua","tony@starkind.xyz","stark@starkind.xyz","tony.tony@starkind.xyz","stark.stark@starkind.xyz","tony.stark@starkind.xyz","stark.tony@starkind.xyz","t.stark@starkind.xyz","s.tony@starkind.xyz","tony@starkind.pro","stark@starkind.pro","tony.tony@starkind.pro","stark.stark@starkind.pro","tony.stark@starkind.pro","stark.tony@starkind.pro","t.stark@starkind.pro","s.tony@starkind.pro"]}]